{
  "type": "Feature",
  "properties": {
    "gid": "4272025031",
    "lbl": "5468.82",
    "val": 5468.82
  },
  "geometry": {
    "type": "MultiPolygon",
    "coordinates": [
      [
        [
          [
            127.8920308,
            37.6724506
          ],
          [
            127.8914758,
            37.6725401
          ],
          [
            127.8903459,
            37.6721603
          ],
          [
            127.8894859,
            37.6719523
          ],
          [
            127.8887576,
            37.6712581
          ],
          [
            127.8884102,
            37.6711782
          ],
          [
            127.8878787,
            37.6705085
          ],
          [
            127.8867465,
            37.6706412
          ],
          [
            127.8861459,
            37.6707431
          ],
          [
            127.8855658,
            37.6711678
          ],
          [
            127.8855269,
            37.6714719
          ],
          [
            127.8842874,
            37.6716385
          ],
          [
            127.8837425,
            37.6715618
          ],
          [
            127.8835888,
            37.6715697
          ],
          [
            127.882884,
            37.6716338
          ],
          [
            127.8824649,
            37.671778
          ],
          [
            127.8822895,
            37.671828
          ],
          [
            127.8813932,
            37.6720521
          ],
          [
            127.8800557,
            37.6728678
          ],
          [
            127.8800044,
            37.6728668
          ],
          [
            127.8796663,
            37.6728589
          ],
          [
            127.8781887,
            37.6715435
          ],
          [
            127.8776679,
            37.6710857
          ],
          [
            127.8775792,
            37.6710075
          ],
          [
            127.877267,
            37.6707226
          ],
          [
            127.8760498,
            37.6702547
          ],
          [
            127.8756221,
            37.6701216
          ],
          [
            127.8752072,
            37.6704412
          ],
          [
            127.8746934,
            37.670459
          ],
          [
            127.8746478,
            37.6704608
          ],
          [
            127.8743652,
            37.6704705
          ],
          [
            127.8742976,
            37.670473
          ],
          [
            127.8741818,
            37.6704769
          ],
          [
            127.8737525,
            37.6704088
          ],
          [
            127.8736992,
            37.6703932
          ],
          [
            127.8735787,
            37.6703578
          ],
          [
            127.8733924,
            37.6703026
          ],
          [
            127.8733476,
            37.6702894
          ],
          [
            127.8732542,
            37.6702619
          ],
          [
            127.8731017,
            37.6702169
          ],
          [
            127.8730762,
            37.6702187
          ],
          [
            127.8730745,
            37.6702813
          ],
          [
            127.8730672,
            37.670542
          ],
          [
            127.873215,
            37.6707898
          ],
          [
            127.8733527,
            37.6713916
          ],
          [
            127.8734175,
            37.6715065
          ],
          [
            127.8733465,
            37.6715251
          ],
          [
            127.8732462,
            37.6715509
          ],
          [
            127.873195,
            37.6715636
          ],
          [
            127.873245,
            37.6716886
          ],
          [
            127.8733169,
            37.6719904
          ],
          [
            127.8734116,
            37.6723684
          ],
          [
            127.873517,
            37.6727744
          ],
          [
            127.87361,
            37.6730688
          ],
          [
            127.8735589,
            37.6730889
          ],
          [
            127.8734278,
            37.6731473
          ],
          [
            127.8733372,
            37.6731849
          ],
          [
            127.8732742,
            37.6730032
          ],
          [
            127.8732436,
            37.6728117
          ],
          [
            127.8725459,
            37.6727312
          ],
          [
            127.8720287,
            37.6727246
          ],
          [
            127.8715777,
            37.6727189
          ],
          [
            127.8714964,
            37.6727007
          ],
          [
            127.8713863,
            37.6726759
          ],
          [
            127.8703095,
            37.6724346
          ],
          [
            127.8696527,
            37.6725132
          ],
          [
            127.8690126,
            37.6723879
          ],
          [
            127.86884,
            37.6717734
          ],
          [
            127.8687503,
            37.6716133
          ],
          [
            127.8686341,
            37.67143
          ],
          [
            127.8681178,
            37.6714043
          ],
          [
            127.8677854,
            37.6712451
          ],
          [
            127.8678243,
            37.6709914
          ],
          [
            127.8680791,
            37.6703921
          ],
          [
            127.8680921,
            37.6701122
          ],
          [
            127.8679579,
            37.6698702
          ],
          [
            127.8677872,
            37.6697171
          ],
          [
            127.8678609,
            37.6692951
          ],
          [
            127.867662,
            37.6688174
          ],
          [
            127.8676591,
            37.6684466
          ],
          [
            127.8677711,
            37.6679069
          ],
          [
            127.8677382,
            37.6675459
          ],
          [
            127.8677853,
            37.6670287
          ],
          [
            127.8675128,
            37.6664346
          ],
          [
            127.8670561,
            37.665755
          ],
          [
            127.8673575,
            37.6651376
          ],
          [
            127.8675839,
            37.6649076
          ],
          [
            127.86742,
            37.6644552
          ],
          [
            127.8671719,
            37.6639536
          ],
          [
            127.867086,
            37.6637169
          ],
          [
            127.8668122,
            37.6628974
          ],
          [
            127.8671463,
            37.6622651
          ],
          [
            127.867397,
            37.6615315
          ],
          [
            127.8669367,
            37.6608955
          ],
          [
            127.866449,
            37.6604953
          ],
          [
            127.8663976,
            37.6602482
          ],
          [
            127.8657856,
            37.6597586
          ],
          [
            127.8655274,
            37.6594528
          ],
          [
            127.8651637,
            37.6590528
          ],
          [
            127.8649928,
            37.6588525
          ],
          [
            127.8649175,
            37.6587458
          ],
          [
            127.8646919,
            37.6587384
          ],
          [
            127.8636886,
            37.6590476
          ],
          [
            127.8635274,
            37.6589789
          ],
          [
            127.863032,
            37.6583088
          ],
          [
            127.8627598,
            37.658139
          ],
          [
            127.8623691,
            37.6577322
          ],
          [
            127.8618788,
            37.6571361
          ],
          [
            127.8616466,
            37.6571708
          ],
          [
            127.8613022,
            37.6570055
          ],
          [
            127.8610185,
            37.6568766
          ],
          [
            127.8606053,
            37.6567929
          ],
          [
            127.860107,
            37.6566952
          ],
          [
            127.859672,
            37.6565624
          ],
          [
            127.8592715,
            37.6564403
          ],
          [
            127.8578909,
            37.6554666
          ],
          [
            127.8573465,
            37.6546006
          ],
          [
            127.8575446,
            37.6542415
          ],
          [
            127.857284,
            37.6535964
          ],
          [
            127.8574521,
            37.653029
          ],
          [
            127.8570847,
            37.6526468
          ],
          [
            127.8559728,
            37.6521847
          ],
          [
            127.8558561,
            37.6518832
          ],
          [
            127.8560424,
            37.6516129
          ],
          [
            127.8560202,
            37.6507823
          ],
          [
            127.8554891,
            37.6498038
          ],
          [
            127.8554757,
            37.6498047
          ],
          [
            127.8547956,
            37.6498451
          ],
          [
            127.8541368,
            37.6499549
          ],
          [
            127.8537362,
            37.6494212
          ],
          [
            127.8524764,
            37.6491149
          ],
          [
            127.8523611,
            37.6492191
          ],
          [
            127.8515653,
            37.6499844
          ],
          [
            127.8514326,
            37.6501166
          ],
          [
            127.8510426,
            37.6504494
          ],
          [
            127.8499946,
            37.6518278
          ],
          [
            127.8494527,
            37.6521312
          ],
          [
            127.8493043,
            37.6524395
          ],
          [
            127.84878,
            37.6525787
          ],
          [
            127.8482868,
            37.6528046
          ],
          [
            127.8477796,
            37.6527353
          ],
          [
            127.847519,
            37.6525176
          ],
          [
            127.8469865,
            37.6523029
          ],
          [
            127.8463133,
            37.6518004
          ],
          [
            127.8460638,
            37.6517203
          ],
          [
            127.8458303,
            37.6517698
          ],
          [
            127.8451092,
            37.6516995
          ],
          [
            127.8447963,
            37.6518082
          ],
          [
            127.8443636,
            37.6522468
          ],
          [
            127.8436652,
            37.6522042
          ],
          [
            127.8434603,
            37.6522775
          ],
          [
            127.8428786,
            37.6527575
          ],
          [
            127.8424992,
            37.6528739
          ],
          [
            127.8418375,
            37.6526981
          ],
          [
            127.841398,
            37.6527227
          ],
          [
            127.8412085,
            37.6528482
          ],
          [
            127.840683,
            37.6528773
          ],
          [
            127.8402775,
            37.6528148
          ],
          [
            127.8400274,
            37.6527701
          ],
          [
            127.8398754,
            37.6526685
          ],
          [
            127.8396962,
            37.6525447
          ],
          [
            127.8396325,
            37.6522
          ],
          [
            127.8392609,
            37.6518766
          ],
          [
            127.839269,
            37.6516167
          ],
          [
            127.8391162,
            37.6514401
          ],
          [
            127.8391158,
            37.6514376
          ],
          [
            127.839218,
            37.6513983
          ],
          [
            127.8391452,
            37.6513155
          ],
          [
            127.8389788,
            37.6511244
          ],
          [
            127.8387329,
            37.6509842
          ],
          [
            127.8385604,
            37.6508863
          ],
          [
            127.8385134,
            37.6505505
          ],
          [
            127.8386065,
            37.6505462
          ],
          [
            127.8386196,
            37.6504171
          ],
          [
            127.8386541,
            37.6503665
          ],
          [
            127.8386823,
            37.6503294
          ],
          [
            127.8386852,
            37.6502077
          ],
          [
            127.8386323,
            37.6500029
          ],
          [
            127.8384732,
            37.6497436
          ],
          [
            127.8383263,
            37.649494
          ],
          [
            127.8377852,
            37.6491482
          ],
          [
            127.8376134,
            37.6490416
          ],
          [
            127.8373938,
            37.64885
          ],
          [
            127.8371886,
            37.6486116
          ],
          [
            127.8368388,
            37.6481427
          ],
          [
            127.8367173,
            37.6476957
          ],
          [
            127.8364947,
            37.6474264
          ],
          [
            127.8363932,
            37.6473086
          ],
          [
            127.83595,
            37.646846
          ],
          [
            127.835605,
            37.6466457
          ],
          [
            127.8349325,
            37.6463512
          ],
          [
            127.8348345,
            37.6462914
          ],
          [
            127.8347268,
            37.6459104
          ],
          [
            127.8346388,
            37.6457674
          ],
          [
            127.8344349,
            37.6456069
          ],
          [
            127.8343647,
            37.6456626
          ],
          [
            127.8333628,
            37.6449182
          ],
          [
            127.8326946,
            37.6442771
          ],
          [
            127.8325352,
            37.6441104
          ],
          [
            127.8325796,
            37.6440901
          ],
          [
            127.8324557,
            37.6439319
          ],
          [
            127.832304,
            37.6435723
          ],
          [
            127.8320253,
            37.6433096
          ],
          [
            127.8317646,
            37.643049
          ],
          [
            127.8315035,
            37.642813
          ],
          [
            127.8312108,
            37.6423752
          ],
          [
            127.8310121,
            37.6414515
          ],
          [
            127.8305574,
            37.6409634
          ],
          [
            127.8302468,
            37.6403797
          ],
          [
            127.8310971,
            37.6400789
          ],
          [
            127.8322207,
            37.6399696
          ],
          [
            127.8324307,
            37.6398158
          ],
          [
            127.8327103,
            37.639842
          ],
          [
            127.8331709,
            37.6396484
          ],
          [
            127.8337017,
            37.6397472
          ],
          [
            127.8337396,
            37.6394935
          ],
          [
            127.8338284,
            37.6393625
          ],
          [
            127.833901,
            37.6391126
          ],
          [
            127.83414,
            37.6390171
          ],
          [
            127.8343053,
            37.6386328
          ],
          [
            127.8347365,
            37.6384746
          ],
          [
            127.8354997,
            37.6369674
          ],
          [
            127.8358266,
            37.6366017
          ],
          [
            127.8361912,
            37.6365025
          ],
          [
            127.8365058,
            37.6360771
          ],
          [
            127.8361612,
            37.635778
          ],
          [
            127.8362024,
            37.6354162
          ],
          [
            127.8353284,
            37.634667
          ],
          [
            127.8352545,
            37.6342567
          ],
          [
            127.8353851,
            37.6340683
          ],
          [
            127.835534,
            37.6336128
          ],
          [
            127.8342108,
            37.6313718
          ],
          [
            127.8355407,
            37.6301267
          ],
          [
            127.83595,
            37.6296184
          ],
          [
            127.8362168,
            37.6286001
          ],
          [
            127.8365044,
            37.6278804
          ],
          [
            127.8359873,
            37.6273894
          ],
          [
            127.8360134,
            37.6261749
          ],
          [
            127.8355546,
            37.6258541
          ],
          [
            127.8354542,
            37.6250394
          ],
          [
            127.835481,
            37.6248072
          ],
          [
            127.8359088,
            37.6243869
          ],
          [
            127.8359347,
            37.6242029
          ],
          [
            127.835289,
            37.6234363
          ],
          [
            127.8352194,
            37.6228472
          ],
          [
            127.8352726,
            37.6223122
          ],
          [
            127.8349362,
            37.6219514
          ],
          [
            127.8354598,
            37.6211408
          ],
          [
            127.835363,
            37.6197309
          ],
          [
            127.8382054,
            37.618952
          ],
          [
            127.8384356,
            37.6190923
          ],
          [
            127.8401789,
            37.6175153
          ],
          [
            127.8401153,
            37.616958
          ],
          [
            127.8403267,
            37.6167521
          ],
          [
            127.840985,
            37.615742
          ],
          [
            127.8411887,
            37.6156007
          ],
          [
            127.8417288,
            37.6155639
          ],
          [
            127.8427883,
            37.6150428
          ],
          [
            127.8442756,
            37.6139854
          ],
          [
            127.8444214,
            37.6138869
          ],
          [
            127.844612,
            37.6136496
          ],
          [
            127.8449999,
            37.6132138
          ],
          [
            127.8454157,
            37.6125802
          ],
          [
            127.8455084,
            37.612896
          ],
          [
            127.8476822,
            37.6128258
          ],
          [
            127.8495683,
            37.6138002
          ],
          [
            127.8496838,
            37.613966
          ],
          [
            127.8501837,
            37.615284
          ],
          [
            127.8507342,
            37.6156092
          ],
          [
            127.851233,
            37.6155884
          ],
          [
            127.8520278,
            37.6156359
          ],
          [
            127.8527083,
            37.6149705
          ],
          [
            127.8556216,
            37.6142386
          ],
          [
            127.8569634,
            37.6133743
          ],
          [
            127.8570046,
            37.6133208
          ],
          [
            127.857301,
            37.612661
          ],
          [
            127.8583223,
            37.6130173
          ],
          [
            127.859065,
            37.6130972
          ],
          [
            127.8594444,
            37.6137108
          ],
          [
            127.8595663,
            37.6138118
          ],
          [
            127.8601763,
            37.614228
          ],
          [
            127.8610308,
            37.6149457
          ],
          [
            127.8621384,
            37.6154171
          ],
          [
            127.8627158,
            37.6155508
          ],
          [
            127.8633318,
            37.615778
          ],
          [
            127.8636595,
            37.6160862
          ],
          [
            127.8646834,
            37.6164748
          ],
          [
            127.8649614,
            37.6165823
          ],
          [
            127.865446,
            37.6167421
          ],
          [
            127.8658595,
            37.6174224
          ],
          [
            127.8663184,
            37.6180195
          ],
          [
            127.8668738,
            37.618328
          ],
          [
            127.8669901,
            37.6183719
          ],
          [
            127.8671972,
            37.6185348
          ],
          [
            127.8672466,
            37.6185221
          ],
          [
            127.8672704,
            37.6185233
          ],
          [
            127.867279,
            37.6186891
          ],
          [
            127.8674437,
            37.6185474
          ],
          [
            127.8675349,
            37.618469
          ],
          [
            127.8677378,
            37.6187814
          ],
          [
            127.8678128,
            37.6191514
          ],
          [
            127.8678712,
            37.6192391
          ],
          [
            127.8679854,
            37.6193202
          ],
          [
            127.8680471,
            37.6193639
          ],
          [
            127.8684476,
            37.6202622
          ],
          [
            127.8693888,
            37.6201731
          ],
          [
            127.8697619,
            37.6201377
          ],
          [
            127.8701424,
            37.6200465
          ],
          [
            127.8705788,
            37.6203183
          ],
          [
            127.8708644,
            37.6204961
          ],
          [
            127.8716359,
            37.6204882
          ],
          [
            127.8726003,
            37.6202587
          ],
          [
            127.8727023,
            37.6203325
          ],
          [
            127.8730094,
            37.6204654
          ],
          [
            127.8740247,
            37.6206322
          ],
          [
            127.8747018,
            37.6208685
          ],
          [
            127.8752918,
            37.6212019
          ],
          [
            127.8753093,
            37.6215149
          ],
          [
            127.8755325,
            37.6217131
          ],
          [
            127.8754207,
            37.6221751
          ],
          [
            127.875416,
            37.6224086
          ],
          [
            127.8763664,
            37.623097
          ],
          [
            127.8759621,
            37.6233939
          ],
          [
            127.8760437,
            37.6241343
          ],
          [
            127.8759293,
            37.6244024
          ],
          [
            127.8760875,
            37.624672
          ],
          [
            127.8754023,
            37.6253427
          ],
          [
            127.8754183,
            37.6255664
          ],
          [
            127.8755982,
            37.625756
          ],
          [
            127.8753161,
            37.6266959
          ],
          [
            127.8749334,
            37.6272934
          ],
          [
            127.8742417,
            37.6280243
          ],
          [
            127.8739098,
            37.6290353
          ],
          [
            127.8733641,
            37.6295024
          ],
          [
            127.873376,
            37.6299182
          ],
          [
            127.8727342,
            37.6307329
          ],
          [
            127.8728561,
            37.6318042
          ],
          [
            127.8732435,
            37.6321504
          ],
          [
            127.8736638,
            37.632912
          ],
          [
            127.8735823,
            37.6336663
          ],
          [
            127.8735976,
            37.6346711
          ],
          [
            127.8728875,
            37.6353422
          ],
          [
            127.8725312,
            37.6355419
          ],
          [
            127.8725194,
            37.6361684
          ],
          [
            127.8715634,
            37.6370454
          ],
          [
            127.8716466,
            37.6372824
          ],
          [
            127.8716567,
            37.638033
          ],
          [
            127.8714227,
            37.6383019
          ],
          [
            127.8721275,
            37.6385673
          ],
          [
            127.8730947,
            37.6391683
          ],
          [
            127.8735581,
            37.6394703
          ],
          [
            127.8739759,
            37.6387484
          ],
          [
            127.8739998,
            37.638333
          ],
          [
            127.8736661,
            37.6383847
          ],
          [
            127.8739777,
            37.6382605
          ],
          [
            127.8749921,
            37.6383273
          ],
          [
            127.8754492,
            37.6383034
          ],
          [
            127.8758791,
            37.6382808
          ],
          [
            127.8764858,
            37.6384182
          ],
          [
            127.8768488,
            37.6386942
          ],
          [
            127.8772434,
            37.6388005
          ],
          [
            127.87749,
            37.6388178
          ],
          [
            127.8779556,
            37.6386978
          ],
          [
            127.8782479,
            37.6386574
          ],
          [
            127.8787806,
            37.6385836
          ],
          [
            127.8799673,
            37.6390033
          ],
          [
            127.8808315,
            37.6392392
          ],
          [
            127.8816338,
            37.6392983
          ],
          [
            127.8818549,
            37.6393811
          ],
          [
            127.8818902,
            37.6393966
          ],
          [
            127.8819045,
            37.6393194
          ],
          [
            127.881961,
            37.6392505
          ],
          [
            127.8820322,
            37.6392477
          ],
          [
            127.8822432,
            37.6392763
          ],
          [
            127.8823882,
            37.6393245
          ],
          [
            127.8825073,
            37.6393993
          ],
          [
            127.8825413,
            37.6394579
          ],
          [
            127.8826176,
            37.6395069
          ],
          [
            127.8828742,
            37.6395295
          ],
          [
            127.882961,
            37.6392602
          ],
          [
            127.8829526,
            37.6386375
          ],
          [
            127.8828259,
            37.6382223
          ],
          [
            127.882764,
            37.6380201
          ],
          [
            127.8839331,
            37.6379041
          ],
          [
            127.8844654,
            37.6380394
          ],
          [
            127.8847363,
            37.6379482
          ],
          [
            127.8849779,
            37.6377594
          ],
          [
            127.8850009,
            37.6376917
          ],
          [
            127.8864304,
            37.6378006
          ],
          [
            127.8864603,
            37.6385944
          ],
          [
            127.8866976,
            37.6384208
          ],
          [
            127.8867257,
            37.6382863
          ],
          [
            127.8869563,
            37.6381182
          ],
          [
            127.8870736,
            37.6381545
          ],
          [
            127.8872817,
            37.637995
          ],
          [
            127.88733,
            37.6380712
          ],
          [
            127.8873664,
            37.6381573
          ],
          [
            127.8876261,
            37.6383148
          ],
          [
            127.8878853,
            37.6378128
          ],
          [
            127.8880368,
            37.6377221
          ],
          [
            127.8887181,
            37.6373164
          ],
          [
            127.8890026,
            37.6372771
          ],
          [
            127.8897009,
            37.6373453
          ],
          [
            127.8896555,
            37.6376612
          ],
          [
            127.8896466,
            37.6377232
          ],
          [
            127.8895679,
            37.6377106
          ],
          [
            127.8891518,
            37.6387763
          ],
          [
            127.888471,
            37.6391916
          ],
          [
            127.8880085,
            37.6394552
          ],
          [
            127.8885217,
            37.6400027
          ],
          [
            127.8887073,
            37.6404284
          ],
          [
            127.8887277,
            37.6404758
          ],
          [
            127.8887241,
            37.6409742
          ],
          [
            127.8889654,
            37.6415298
          ],
          [
            127.8890852,
            37.6418054
          ],
          [
            127.8896067,
            37.6422531
          ],
          [
            127.8891888,
            37.6425986
          ],
          [
            127.8892276,
            37.6428855
          ],
          [
            127.8895291,
            37.6430473
          ],
          [
            127.8898665,
            37.6433131
          ],
          [
            127.8906093,
            37.6433106
          ],
          [
            127.891351,
            37.6434227
          ],
          [
            127.8915636,
            37.6433752
          ],
          [
            127.8916755,
            37.6433499
          ],
          [
            127.8922845,
            37.6436772
          ],
          [
            127.8935877,
            37.6443771
          ],
          [
            127.8936849,
            37.6443612
          ],
          [
            127.8938422,
            37.6443068
          ],
          [
            127.8941451,
            37.6441432
          ],
          [
            127.8944929,
            37.6439423
          ],
          [
            127.8952559,
            37.6437395
          ],
          [
            127.8954849,
            37.6434948
          ],
          [
            127.895735,
            37.6433848
          ],
          [
            127.8958948,
            37.6433655
          ],
          [
            127.8969333,
            37.6432228
          ],
          [
            127.897129,
            37.6435068
          ],
          [
            127.8974284,
            37.6439409
          ],
          [
            127.8976838,
            37.6440609
          ],
          [
            127.8981701,
            37.6442813
          ],
          [
            127.8981413,
            37.6444164
          ],
          [
            127.8979897,
            37.6451245
          ],
          [
            127.8981055,
            37.6451836
          ],
          [
            127.8984653,
            37.6452774
          ],
          [
            127.8990109,
            37.64542
          ],
          [
            127.8995611,
            37.645567
          ],
          [
            127.8999508,
            37.6456713
          ],
          [
            127.9001553,
            37.6460368
          ],
          [
            127.9010741,
            37.6464798
          ],
          [
            127.9006814,
            37.6468885
          ],
          [
            127.9005171,
            37.6470001
          ],
          [
            127.8998534,
            37.6474908
          ],
          [
            127.899904,
            37.6478401
          ],
          [
            127.9000064,
            37.6483771
          ],
          [
            127.9000966,
            37.6485735
          ],
          [
            127.9002025,
            37.6487849
          ],
          [
            127.8999787,
            37.6491656
          ],
          [
            127.8999643,
            37.6492865
          ],
          [
            127.8999637,
            37.6493884
          ],
          [
            127.8999568,
            37.649757
          ],
          [
            127.8999482,
            37.649982
          ],
          [
            127.8999165,
            37.6500845
          ],
          [
            127.8996954,
            37.650803
          ],
          [
            127.8990849,
            37.6513308
          ],
          [
            127.8990178,
            37.6514059
          ],
          [
            127.898902,
            37.651585
          ],
          [
            127.898529,
            37.6521613
          ],
          [
            127.898157,
            37.6529975
          ],
          [
            127.8981841,
            37.6533968
          ],
          [
            127.8981879,
            37.6534514
          ],
          [
            127.8978406,
            37.6536936
          ],
          [
            127.897778,
            37.6539394
          ],
          [
            127.8976079,
            37.6546051
          ],
          [
            127.8977025,
            37.6547519
          ],
          [
            127.897735,
            37.6551624
          ],
          [
            127.8966507,
            37.6559618
          ],
          [
            127.8967601,
            37.6566964
          ],
          [
            127.8971377,
            37.6573805
          ],
          [
            127.8971359,
            37.6574413
          ],
          [
            127.8971302,
            37.657641
          ],
          [
            127.8964129,
            37.6580071
          ],
          [
            127.8962458,
            37.6583991
          ],
          [
            127.8959901,
            37.6585199
          ],
          [
            127.8954321,
            37.6592632
          ],
          [
            127.895302,
            37.6597279
          ],
          [
            127.894676,
            37.6604767
          ],
          [
            127.8949663,
            37.6608808
          ],
          [
            127.8948902,
            37.6611798
          ],
          [
            127.8951576,
            37.6616257
          ],
          [
            127.8949737,
            37.6618577
          ],
          [
            127.8948905,
            37.6625946
          ],
          [
            127.8947104,
            37.6627851
          ],
          [
            127.8948188,
            37.6629068
          ],
          [
            127.8954533,
            37.6635771
          ],
          [
            127.8958468,
            37.6637543
          ],
          [
            127.8961747,
            37.6643361
          ],
          [
            127.8964928,
            37.6648998
          ],
          [
            127.8963469,
            37.6654652
          ],
          [
            127.8962522,
            37.6658333
          ],
          [
            127.8962132,
            37.6659845
          ],
          [
            127.8962106,
            37.6663812
          ],
          [
            127.8962019,
            37.6666321
          ],
          [
            127.8961412,
            37.6668288
          ],
          [
            127.8958585,
            37.6669411
          ],
          [
            127.8957199,
            37.6668683
          ],
          [
            127.8955576,
            37.6668617
          ],
          [
            127.895437,
            37.6668817
          ],
          [
            127.895165,
            37.6676778
          ],
          [
            127.894949,
            37.6677143
          ],
          [
            127.894732,
            37.6677512
          ],
          [
            127.8944501,
            37.6676624
          ],
          [
            127.8938692,
            37.6678985
          ],
          [
            127.8934259,
            37.6690024
          ],
          [
            127.8932141,
            37.6695071
          ],
          [
            127.8929844,
            37.6700531
          ],
          [
            127.8926985,
            37.6703438
          ],
          [
            127.8921343,
            37.6706212
          ],
          [
            127.8921143,
            37.6707793
          ],
          [
            127.8920699,
            37.671011
          ],
          [
            127.8920697,
            37.6711693
          ],
          [
            127.8920213,
            37.6715041
          ],
          [
            127.8920308,
            37.6724506
          ]
        ]
      ]
    ]
  }
}