{
  "type": "Feature",
  "properties": {
    "gid": "4613035030",
    "lbl": "8373.49",
    "val": 8373.49,
    "gidInfo": {
      "fullCode": "4613035030",
      "fullName": "전라남도 여수시 화정면 여자리",
      "cityCode": "46",
      "subCode": "130",
      "sub2Code": "350",
      "code": "30",
      "isAlive": true,
      "name": "여자리",
      "type": "리"
    }
  },
  "geometry": {
    "type": "MultiPolygon",
    "coordinates": [
      [
        [
          [
            127.4690878,
            34.7455193
          ],
          [
            127.4683539,
            34.7464129
          ],
          [
            127.4676188,
            34.747077
          ],
          [
            127.46791,
            34.7462865
          ],
          [
            127.4680153,
            34.7459338
          ],
          [
            127.4682857,
            34.7450527
          ],
          [
            127.4691968,
            34.744655
          ],
          [
            127.4690878,
            34.7455193
          ]
        ]
      ],
      [
        [
          [
            127.5161734,
            34.7496925
          ],
          [
            127.515919,
            34.7498973
          ],
          [
            127.5157501,
            34.7497738
          ],
          [
            127.515971,
            34.7495368
          ],
          [
            127.5161734,
            34.7496925
          ]
        ]
      ],
      [
        [
          [
            127.4957263,
            34.7530519
          ],
          [
            127.4959522,
            34.7532559
          ],
          [
            127.4953823,
            34.7538019
          ],
          [
            127.4946694,
            34.7541938
          ],
          [
            127.4949807,
            34.753425
          ],
          [
            127.4956094,
            34.7530279
          ],
          [
            127.4957263,
            34.7530519
          ]
        ]
      ],
      [
        [
          [
            127.4807734,
            34.7542982
          ],
          [
            127.4805189,
            34.7545028
          ],
          [
            127.4803499,
            34.7543793
          ],
          [
            127.4805711,
            34.7541424
          ],
          [
            127.4807734,
            34.7542982
          ]
        ]
      ],
      [
        [
          [
            127.5080595,
            34.7549855
          ],
          [
            127.5079254,
            34.7551239
          ],
          [
            127.5078543,
            34.7551598
          ],
          [
            127.507492,
            34.7551533
          ],
          [
            127.5074592,
            34.7550591
          ],
          [
            127.507515,
            34.7549615
          ],
          [
            127.5075617,
            34.7548932
          ],
          [
            127.507627,
            34.754853
          ],
          [
            127.5079466,
            34.7548437
          ],
          [
            127.5080595,
            34.7549855
          ]
        ]
      ],
      [
        [
          [
            127.5111816,
            34.7561713
          ],
          [
            127.5110908,
            34.756183
          ],
          [
            127.5109791,
            34.756146
          ],
          [
            127.511011,
            34.7560296
          ],
          [
            127.5111134,
            34.7559342
          ],
          [
            127.5112661,
            34.7558735
          ],
          [
            127.5112988,
            34.7558379
          ],
          [
            127.511367,
            34.7558471
          ],
          [
            127.5114226,
            34.7559176
          ],
          [
            127.5113735,
            34.755966
          ],
          [
            127.5113807,
            34.7560324
          ],
          [
            127.5113584,
            34.7560765
          ],
          [
            127.5113012,
            34.7560831
          ],
          [
            127.5112991,
            34.7561197
          ],
          [
            127.5112536,
            34.7561145
          ],
          [
            127.5111816,
            34.7561713
          ]
        ]
      ],
      [
        [
          [
            127.5130268,
            34.75656
          ],
          [
            127.5129835,
            34.7565904
          ],
          [
            127.5127688,
            34.7561462
          ],
          [
            127.5128188,
            34.756123
          ],
          [
            127.5130268,
            34.75656
          ]
        ]
      ],
      [
        [
          [
            127.5113041,
            34.7608075
          ],
          [
            127.5111869,
            34.7610591
          ],
          [
            127.5107678,
            34.7612959
          ],
          [
            127.5105176,
            34.7613334
          ],
          [
            127.510335,
            34.7611733
          ],
          [
            127.5107936,
            34.7607948
          ],
          [
            127.5103023,
            34.7604867
          ],
          [
            127.510172,
            34.7605108
          ],
          [
            127.5099824,
            34.7605858
          ],
          [
            127.5099597,
            34.7606104
          ],
          [
            127.5098793,
            34.7606686
          ],
          [
            127.5098058,
            34.7606936
          ],
          [
            127.5097036,
            34.7606957
          ],
          [
            127.5097192,
            34.7606594
          ],
          [
            127.509642,
            34.7605744
          ],
          [
            127.5095967,
            34.7603851
          ],
          [
            127.5096235,
            34.7603019
          ],
          [
            127.50964,
            34.7601853
          ],
          [
            127.5097359,
            34.7600429
          ],
          [
            127.5098201,
            34.7599304
          ],
          [
            127.5098917,
            34.7598676
          ],
          [
            127.5100551,
            34.7597434
          ],
          [
            127.5101261,
            34.7596461
          ],
          [
            127.5101806,
            34.7595979
          ],
          [
            127.51014,
            34.7595841
          ],
          [
            127.5100154,
            34.7593851
          ],
          [
            127.5098933,
            34.7592217
          ],
          [
            127.5099522,
            34.7591873
          ],
          [
            127.5098976,
            34.7591285
          ],
          [
            127.5098712,
            34.7591128
          ],
          [
            127.509682,
            34.7589687
          ],
          [
            127.5094945,
            34.7588604
          ],
          [
            127.5092633,
            34.7587665
          ],
          [
            127.5091312,
            34.7587018
          ],
          [
            127.509097,
            34.75867
          ],
          [
            127.5090966,
            34.7586328
          ],
          [
            127.5091064,
            34.7585883
          ],
          [
            127.5091644,
            34.7584916
          ],
          [
            127.5093612,
            34.7584012
          ],
          [
            127.5096964,
            34.7583802
          ],
          [
            127.5099267,
            34.7583946
          ],
          [
            127.5101442,
            34.7582829
          ],
          [
            127.5102362,
            34.757946
          ],
          [
            127.5103505,
            34.7577849
          ],
          [
            127.5107817,
            34.7575075
          ],
          [
            127.5110061,
            34.7574811
          ],
          [
            127.5111889,
            34.7575463
          ],
          [
            127.5112352,
            34.7576335
          ],
          [
            127.5112492,
            34.7575747
          ],
          [
            127.5113351,
            34.7575884
          ],
          [
            127.5113531,
            34.7575728
          ],
          [
            127.5113756,
            34.7575861
          ],
          [
            127.5115378,
            34.7574425
          ],
          [
            127.5116885,
            34.757554
          ],
          [
            127.5116977,
            34.7575475
          ],
          [
            127.5117963,
            34.7576441
          ],
          [
            127.5118062,
            34.7576922
          ],
          [
            127.5118116,
            34.7577763
          ],
          [
            127.5120278,
            34.7577883
          ],
          [
            127.5120134,
            34.7577048
          ],
          [
            127.5120075,
            34.7576314
          ],
          [
            127.5121613,
            34.7576027
          ],
          [
            127.5122039,
            34.7576767
          ],
          [
            127.5122372,
            34.7576553
          ],
          [
            127.5123499,
            34.7576108
          ],
          [
            127.512475,
            34.7576016
          ],
          [
            127.5125368,
            34.7575946
          ],
          [
            127.5125851,
            34.757579
          ],
          [
            127.5126588,
            34.7575412
          ],
          [
            127.5127283,
            34.7574939
          ],
          [
            127.512755,
            34.7574634
          ],
          [
            127.512877,
            34.7573336
          ],
          [
            127.5129018,
            34.7572777
          ],
          [
            127.5128982,
            34.7572031
          ],
          [
            127.512865,
            34.757119
          ],
          [
            127.5128002,
            34.7571499
          ],
          [
            127.5127673,
            34.7571048
          ],
          [
            127.5127271,
            34.7570785
          ],
          [
            127.5125732,
            34.7568072
          ],
          [
            127.5122351,
            34.7567322
          ],
          [
            127.5119378,
            34.7566662
          ],
          [
            127.511939,
            34.7566345
          ],
          [
            127.5123688,
            34.7567352
          ],
          [
            127.51256,
            34.7567704
          ],
          [
            127.5126333,
            34.7566929
          ],
          [
            127.5127529,
            34.7567239
          ],
          [
            127.512861,
            34.7565957
          ],
          [
            127.5130743,
            34.7568026
          ],
          [
            127.5135981,
            34.7567238
          ],
          [
            127.5138526,
            34.7566576
          ],
          [
            127.5140602,
            34.7565238
          ],
          [
            127.5142269,
            34.7563994
          ],
          [
            127.5143628,
            34.7562649
          ],
          [
            127.5144996,
            34.7560108
          ],
          [
            127.51469,
            34.7556552
          ],
          [
            127.5147364,
            34.7555978
          ],
          [
            127.5148822,
            34.7554286
          ],
          [
            127.5150317,
            34.7552807
          ],
          [
            127.515615,
            34.7549414
          ],
          [
            127.5159718,
            34.7547139
          ],
          [
            127.5161378,
            34.7547217
          ],
          [
            127.5161338,
            34.7550509
          ],
          [
            127.5161021,
            34.755331
          ],
          [
            127.516048,
            34.7555195
          ],
          [
            127.5158672,
            34.7561422
          ],
          [
            127.5158053,
            34.7562831
          ],
          [
            127.515575,
            34.7566918
          ],
          [
            127.515413,
            34.7569788
          ],
          [
            127.5151996,
            34.7573533
          ],
          [
            127.5148029,
            34.7579082
          ],
          [
            127.514703,
            34.758058
          ],
          [
            127.5145197,
            34.7584144
          ],
          [
            127.5145031,
            34.7584325
          ],
          [
            127.5139557,
            34.7588445
          ],
          [
            127.5137735,
            34.7593188
          ],
          [
            127.5137704,
            34.7593283
          ],
          [
            127.512959,
            34.7594884
          ],
          [
            127.5129277,
            34.7596243
          ],
          [
            127.5129205,
            34.7598224
          ],
          [
            127.5126444,
            34.7601911
          ],
          [
            127.512462,
            34.7604308
          ],
          [
            127.5123126,
            34.7605452
          ],
          [
            127.51215,
            34.7606459
          ],
          [
            127.5121154,
            34.7606367
          ],
          [
            127.5117306,
            34.7604319
          ],
          [
            127.5116666,
            34.7604573
          ],
          [
            127.5113041,
            34.7608075
          ]
        ]
      ],
      [
        [
          [
            127.4905433,
            34.7638517
          ],
          [
            127.4899948,
            34.7641171
          ],
          [
            127.4899669,
            34.7640803
          ],
          [
            127.4905154,
            34.7638119
          ],
          [
            127.4905433,
            34.7638517
          ]
        ]
      ],
      [
        [
          [
            127.5048008,
            34.7639939
          ],
          [
            127.504977,
            34.7646475
          ],
          [
            127.5055004,
            34.7648836
          ],
          [
            127.505931,
            34.7651161
          ],
          [
            127.5059004,
            34.7658175
          ],
          [
            127.5056216,
            34.7661709
          ],
          [
            127.5052881,
            34.7662659
          ],
          [
            127.5052042,
            34.7659333
          ],
          [
            127.505058,
            34.7653971
          ],
          [
            127.5046909,
            34.7648955
          ],
          [
            127.5043408,
            34.7642736
          ],
          [
            127.5046524,
            34.7639791
          ],
          [
            127.5048008,
            34.7639939
          ]
        ]
      ],
      [
        [
          [
            127.4918945,
            34.7669136
          ],
          [
            127.4919092,
            34.7669643
          ],
          [
            127.4918687,
            34.7669958
          ],
          [
            127.4918369,
            34.7670068
          ],
          [
            127.4914183,
            34.7671854
          ],
          [
            127.4913586,
            34.7671989
          ],
          [
            127.4913039,
            34.7671798
          ],
          [
            127.4911857,
            34.7670749
          ],
          [
            127.4911621,
            34.7670569
          ],
          [
            127.491106,
            34.7669832
          ],
          [
            127.4910337,
            34.7669315
          ],
          [
            127.4910201,
            34.7669115
          ],
          [
            127.4910179,
            34.7668901
          ],
          [
            127.491004,
            34.7668114
          ],
          [
            127.4909587,
            34.7667471
          ],
          [
            127.4908571,
            34.7666527
          ],
          [
            127.4907811,
            34.7666076
          ],
          [
            127.4904748,
            34.7664205
          ],
          [
            127.4903327,
            34.7663088
          ],
          [
            127.4902884,
            34.7662925
          ],
          [
            127.4902593,
            34.7662687
          ],
          [
            127.4901289,
            34.7660064
          ],
          [
            127.4900941,
            34.765874
          ],
          [
            127.4900837,
            34.7657365
          ],
          [
            127.4901059,
            34.7656631
          ],
          [
            127.4901781,
            34.7655139
          ],
          [
            127.4897641,
            34.7652525
          ],
          [
            127.489449,
            34.7650574
          ],
          [
            127.4895374,
            34.7649393
          ],
          [
            127.4895752,
            34.7649581
          ],
          [
            127.4895171,
            34.7650339
          ],
          [
            127.4896364,
            34.7651161
          ],
          [
            127.4898692,
            34.7652772
          ],
          [
            127.490201,
            34.7654864
          ],
          [
            127.4903179,
            34.7655599
          ],
          [
            127.4904514,
            34.7653188
          ],
          [
            127.4904826,
            34.7653333
          ],
          [
            127.4903486,
            34.7655785
          ],
          [
            127.4904802,
            34.7656415
          ],
          [
            127.4905774,
            34.7658176
          ],
          [
            127.4907336,
            34.7659675
          ],
          [
            127.4908113,
            34.7659665
          ],
          [
            127.4909745,
            34.7660883
          ],
          [
            127.4913783,
            34.7663758
          ],
          [
            127.4915719,
            34.7663597
          ],
          [
            127.4916789,
            34.766333
          ],
          [
            127.4917016,
            34.7663221
          ],
          [
            127.4917868,
            34.7662738
          ],
          [
            127.4918178,
            34.7662575
          ],
          [
            127.491883,
            34.7662049
          ],
          [
            127.4920013,
            34.7661164
          ],
          [
            127.4921708,
            34.7658994
          ],
          [
            127.4922544,
            34.765785
          ],
          [
            127.4923309,
            34.7656577
          ],
          [
            127.4923535,
            34.7655507
          ],
          [
            127.4923774,
            34.7654633
          ],
          [
            127.4923699,
            34.7653731
          ],
          [
            127.4923522,
            34.7653178
          ],
          [
            127.492352,
            34.7652951
          ],
          [
            127.4922857,
            34.7650761
          ],
          [
            127.4921893,
            34.7650606
          ],
          [
            127.4920098,
            34.7650401
          ],
          [
            127.4920294,
            34.7649391
          ],
          [
            127.4917157,
            34.7648987
          ],
          [
            127.4913922,
            34.7648587
          ],
          [
            127.4909936,
            34.7647934
          ],
          [
            127.4907723,
            34.7650602
          ],
          [
            127.4907444,
            34.7650457
          ],
          [
            127.4909528,
            34.7647897
          ],
          [
            127.4909247,
            34.7647328
          ],
          [
            127.4909073,
            34.7646918
          ],
          [
            127.4908763,
            34.7646302
          ],
          [
            127.4908551,
            34.7645574
          ],
          [
            127.4908529,
            34.7645087
          ],
          [
            127.4908579,
            34.7644593
          ],
          [
            127.4909399,
            34.7644626
          ],
          [
            127.4909485,
            34.7644003
          ],
          [
            127.4910171,
            34.7641793
          ],
          [
            127.4911848,
            34.7640004
          ],
          [
            127.4914087,
            34.7638283
          ],
          [
            127.4915257,
            34.7636873
          ],
          [
            127.4916614,
            34.7635827
          ],
          [
            127.4917306,
            34.7635014
          ],
          [
            127.4917757,
            34.7634756
          ],
          [
            127.4918063,
            34.7634721
          ],
          [
            127.4917853,
            34.7634468
          ],
          [
            127.4918427,
            34.7633665
          ],
          [
            127.491862,
            34.7633224
          ],
          [
            127.4919001,
            34.7632976
          ],
          [
            127.4919285,
            34.7632882
          ],
          [
            127.4920692,
            34.763247
          ],
          [
            127.4921128,
            34.7631744
          ],
          [
            127.4921569,
            34.7631412
          ],
          [
            127.4922626,
            34.7630929
          ],
          [
            127.4923989,
            34.7630073
          ],
          [
            127.492607,
            34.7629387
          ],
          [
            127.4926191,
            34.7629052
          ],
          [
            127.4926285,
            34.7628708
          ],
          [
            127.4926417,
            34.7628492
          ],
          [
            127.492721,
            34.7628596
          ],
          [
            127.4927537,
            34.7628442
          ],
          [
            127.4927949,
            34.7628186
          ],
          [
            127.4928755,
            34.76279
          ],
          [
            127.4928884,
            34.7627856
          ],
          [
            127.4929686,
            34.7627373
          ],
          [
            127.4929843,
            34.7627055
          ],
          [
            127.4930194,
            34.7626774
          ],
          [
            127.4930334,
            34.7626873
          ],
          [
            127.4930538,
            34.7626736
          ],
          [
            127.4930812,
            34.76267
          ],
          [
            127.4930609,
            34.7625704
          ],
          [
            127.493077,
            34.7624922
          ],
          [
            127.4931183,
            34.7623905
          ],
          [
            127.4931007,
            34.7623448
          ],
          [
            127.4931548,
            34.7622841
          ],
          [
            127.4932766,
            34.7621704
          ],
          [
            127.4933624,
            34.7621143
          ],
          [
            127.4934298,
            34.7620863
          ],
          [
            127.4935534,
            34.7620642
          ],
          [
            127.4935966,
            34.7620166
          ],
          [
            127.4935967,
            34.7619707
          ],
          [
            127.4936082,
            34.7619478
          ],
          [
            127.4937357,
            34.7618946
          ],
          [
            127.4938296,
            34.7617408
          ],
          [
            127.4938552,
            34.761691
          ],
          [
            127.4939352,
            34.7616532
          ],
          [
            127.4941915,
            34.7615686
          ],
          [
            127.4944992,
            34.7612624
          ],
          [
            127.4947126,
            34.7609264
          ],
          [
            127.4947487,
            34.7607542
          ],
          [
            127.4947953,
            34.7605962
          ],
          [
            127.4948149,
            34.7605733
          ],
          [
            127.49485,
            34.7604963
          ],
          [
            127.4948463,
            34.7604589
          ],
          [
            127.4947676,
            34.7603054
          ],
          [
            127.4947241,
            34.7601897
          ],
          [
            127.4947285,
            34.7601175
          ],
          [
            127.4948354,
            34.7599914
          ],
          [
            127.4950052,
            34.7599165
          ],
          [
            127.4950578,
            34.7598044
          ],
          [
            127.4952237,
            34.7597424
          ],
          [
            127.4954089,
            34.7598122
          ],
          [
            127.4955372,
            34.7599918
          ],
          [
            127.4957348,
            34.7599822
          ],
          [
            127.49586,
            34.7599445
          ],
          [
            127.4959827,
            34.7598884
          ],
          [
            127.4960323,
            34.7598745
          ],
          [
            127.496091,
            34.7598472
          ],
          [
            127.4961157,
            34.7598147
          ],
          [
            127.4961898,
            34.7598077
          ],
          [
            127.4962669,
            34.7598141
          ],
          [
            127.4963527,
            34.7597786
          ],
          [
            127.4964671,
            34.7597214
          ],
          [
            127.4965115,
            34.7597154
          ],
          [
            127.4965775,
            34.7596862
          ],
          [
            127.4966067,
            34.7596582
          ],
          [
            127.4966514,
            34.7596134
          ],
          [
            127.4967004,
            34.7595869
          ],
          [
            127.4968262,
            34.7595546
          ],
          [
            127.496896,
            34.7595335
          ],
          [
            127.496986,
            34.7594948
          ],
          [
            127.4970712,
            34.7594329
          ],
          [
            127.4971111,
            34.7594242
          ],
          [
            127.4971901,
            34.7593242
          ],
          [
            127.4972915,
            34.7591796
          ],
          [
            127.4973879,
            34.759039
          ],
          [
            127.4973964,
            34.7590267
          ],
          [
            127.4973849,
            34.759006
          ],
          [
            127.4974165,
            34.7589388
          ],
          [
            127.497552,
            34.7586841
          ],
          [
            127.4975836,
            34.7586145
          ],
          [
            127.4975848,
            34.7585734
          ],
          [
            127.4975706,
            34.7585381
          ],
          [
            127.4975681,
            34.7585021
          ],
          [
            127.4975906,
            34.7584578
          ],
          [
            127.4976044,
            34.7583688
          ],
          [
            127.4976046,
            34.7582286
          ],
          [
            127.4976159,
            34.7581655
          ],
          [
            127.4976335,
            34.7581111
          ],
          [
            127.4976339,
            34.7580825
          ],
          [
            127.497626,
            34.758081
          ],
          [
            127.4975764,
            34.7580718
          ],
          [
            127.4975463,
            34.7580574
          ],
          [
            127.4975268,
            34.7580284
          ],
          [
            127.4974974,
            34.7580346
          ],
          [
            127.4974911,
            34.7579966
          ],
          [
            127.4974256,
            34.7578882
          ],
          [
            127.4973859,
            34.7578436
          ],
          [
            127.4973243,
            34.7578229
          ],
          [
            127.4972687,
            34.7577711
          ],
          [
            127.4972114,
            34.7576381
          ],
          [
            127.4972107,
            34.7575525
          ],
          [
            127.497356,
            34.7574025
          ],
          [
            127.4974361,
            34.7573292
          ],
          [
            127.4975155,
            34.7573081
          ],
          [
            127.4975743,
            34.757281
          ],
          [
            127.4975987,
            34.757253
          ],
          [
            127.4975952,
            34.7571564
          ],
          [
            127.4976045,
            34.757105
          ],
          [
            127.4976323,
            34.7570464
          ],
          [
            127.4976751,
            34.7570201
          ],
          [
            127.4977452,
            34.7568955
          ],
          [
            127.4978606,
            34.7567138
          ],
          [
            127.498027,
            34.756566
          ],
          [
            127.498123,
            34.7561934
          ],
          [
            127.4982013,
            34.7560577
          ],
          [
            127.4982673,
            34.755942
          ],
          [
            127.4982519,
            34.7558595
          ],
          [
            127.4977024,
            34.7558115
          ],
          [
            127.4973551,
            34.7557833
          ],
          [
            127.4973676,
            34.7557361
          ],
          [
            127.4977097,
            34.7557675
          ],
          [
            127.4979584,
            34.7557887
          ],
          [
            127.4980401,
            34.7557959
          ],
          [
            127.4982433,
            34.7558135
          ],
          [
            127.4982395,
            34.7557927
          ],
          [
            127.4982008,
            34.7557033
          ],
          [
            127.4984043,
            34.7554279
          ],
          [
            127.4986923,
            34.7553179
          ],
          [
            127.4987176,
            34.7552103
          ],
          [
            127.4988726,
            34.7550498
          ],
          [
            127.4990455,
            34.75497
          ],
          [
            127.4990734,
            34.7549485
          ],
          [
            127.4988949,
            34.7549927
          ],
          [
            127.4988593,
            34.7549955
          ],
          [
            127.4988324,
            34.7549869
          ],
          [
            127.4988019,
            34.7549559
          ],
          [
            127.4986974,
            34.7546753
          ],
          [
            127.4985914,
            34.7544307
          ],
          [
            127.4985247,
            34.7542771
          ],
          [
            127.4984869,
            34.7542107
          ],
          [
            127.4984172,
            34.7540823
          ],
          [
            127.4980202,
            34.7542096
          ],
          [
            127.4978053,
            34.7542619
          ],
          [
            127.4974339,
            34.7543401
          ],
          [
            127.4971366,
            34.7544149
          ],
          [
            127.4971333,
            34.7543798
          ],
          [
            127.4971973,
            34.7543651
          ],
          [
            127.4971863,
            34.7543349
          ],
          [
            127.4973659,
            34.754291
          ],
          [
            127.4977244,
            34.7542056
          ],
          [
            127.4979753,
            34.7541577
          ],
          [
            127.4979877,
            34.7541771
          ],
          [
            127.498416,
            34.7540538
          ],
          [
            127.4984627,
            34.7540515
          ],
          [
            127.498555,
            34.7541009
          ],
          [
            127.4985844,
            34.7540842
          ],
          [
            127.4986215,
            34.7540749
          ],
          [
            127.4987234,
            34.7536466
          ],
          [
            127.498867,
            34.7528985
          ],
          [
            127.4991664,
            34.7522623
          ],
          [
            127.4993504,
            34.7520818
          ],
          [
            127.4993864,
            34.7520559
          ],
          [
            127.4997627,
            34.7523016
          ],
          [
            127.5002155,
            34.7525956
          ],
          [
            127.5001878,
            34.7529998
          ],
          [
            127.5002614,
            34.7531841
          ],
          [
            127.5002946,
            34.7532833
          ],
          [
            127.5003517,
            34.7534409
          ],
          [
            127.5003646,
            34.7534982
          ],
          [
            127.5005225,
            34.7535712
          ],
          [
            127.5006164,
            34.7536363
          ],
          [
            127.5007397,
            34.7537401
          ],
          [
            127.5010877,
            34.7542767
          ],
          [
            127.5011308,
            34.7543232
          ],
          [
            127.5012116,
            34.7543823
          ],
          [
            127.5013272,
            34.7544425
          ],
          [
            127.5014408,
            34.7544934
          ],
          [
            127.5017617,
            34.7545901
          ],
          [
            127.5019753,
            34.7546553
          ],
          [
            127.5022427,
            34.7547407
          ],
          [
            127.5023654,
            34.7547258
          ],
          [
            127.5025364,
            34.7542839
          ],
          [
            127.5026423,
            34.7543251
          ],
          [
            127.5025314,
            34.7544907
          ],
          [
            127.5024355,
            34.7547219
          ],
          [
            127.5025134,
            34.7547867
          ],
          [
            127.5025837,
            34.7548274
          ],
          [
            127.502818,
            34.754935
          ],
          [
            127.5028963,
            34.7549668
          ],
          [
            127.5028767,
            34.7550085
          ],
          [
            127.5029732,
            34.7550464
          ],
          [
            127.5030288,
            34.7550586
          ],
          [
            127.5030786,
            34.7550689
          ],
          [
            127.5031453,
            34.7550928
          ],
          [
            127.5032363,
            34.7551491
          ],
          [
            127.5032888,
            34.7551601
          ],
          [
            127.5033032,
            34.7551811
          ],
          [
            127.5033667,
            34.7551921
          ],
          [
            127.5035599,
            34.7552253
          ],
          [
            127.5036156,
            34.755193
          ],
          [
            127.5036951,
            34.755151
          ],
          [
            127.503855,
            34.7551529
          ],
          [
            127.5040176,
            34.755208
          ],
          [
            127.5041305,
            34.7553081
          ],
          [
            127.5042289,
            34.7553313
          ],
          [
            127.5044062,
            34.7556027
          ],
          [
            127.504415,
            34.7557104
          ],
          [
            127.5043636,
            34.7557779
          ],
          [
            127.5042335,
            34.7558357
          ],
          [
            127.5040087,
            34.7559093
          ],
          [
            127.5038983,
            34.7559666
          ],
          [
            127.5037138,
            34.7560577
          ],
          [
            127.5034499,
            34.7561836
          ],
          [
            127.5034114,
            34.7561943
          ],
          [
            127.5034027,
            34.7562126
          ],
          [
            127.5033222,
            34.7563138
          ],
          [
            127.5033214,
            34.7565226
          ],
          [
            127.5032261,
            34.7567614
          ],
          [
            127.5031515,
            34.7569232
          ],
          [
            127.5031558,
            34.7570171
          ],
          [
            127.5032048,
            34.7570947
          ],
          [
            127.5032626,
            34.7571605
          ],
          [
            127.5033648,
            34.7572227
          ],
          [
            127.5033719,
            34.7572988
          ],
          [
            127.5033415,
            34.7573827
          ],
          [
            127.5032941,
            34.7574486
          ],
          [
            127.5032279,
            34.7575031
          ],
          [
            127.5032192,
            34.757516
          ],
          [
            127.5032026,
            34.7575464
          ],
          [
            127.5031811,
            34.7576088
          ],
          [
            127.5030207,
            34.7577497
          ],
          [
            127.5029667,
            34.7577643
          ],
          [
            127.5028863,
            34.7577267
          ],
          [
            127.5027777,
            34.7577429
          ],
          [
            127.5026517,
            34.7577408
          ],
          [
            127.5025924,
            34.7577674
          ],
          [
            127.5024659,
            34.7577621
          ],
          [
            127.5024489,
            34.7577612
          ],
          [
            127.5023406,
            34.7577428
          ],
          [
            127.5022346,
            34.7577351
          ],
          [
            127.5021395,
            34.757731
          ],
          [
            127.5017093,
            34.7577046
          ],
          [
            127.5015924,
            34.7577027
          ],
          [
            127.5015795,
            34.7576847
          ],
          [
            127.5011157,
            34.7577217
          ],
          [
            127.5010756,
            34.7577193
          ],
          [
            127.5010305,
            34.7577369
          ],
          [
            127.5009586,
            34.757755
          ],
          [
            127.500732,
            34.757801
          ],
          [
            127.5006829,
            34.7578183
          ],
          [
            127.5004292,
            34.7579081
          ],
          [
            127.5004047,
            34.7580214
          ],
          [
            127.5004157,
            34.7580871
          ],
          [
            127.5003627,
            34.7581974
          ],
          [
            127.5001465,
            34.7584826
          ],
          [
            127.5000993,
            34.7585035
          ],
          [
            127.4998769,
            34.7585626
          ],
          [
            127.4998257,
            34.758535
          ],
          [
            127.4997911,
            34.758473
          ],
          [
            127.4996482,
            34.7584731
          ],
          [
            127.499488,
            34.7585583
          ],
          [
            127.4994319,
            34.7585872
          ],
          [
            127.4993969,
            34.758626
          ],
          [
            127.4993473,
            34.7586473
          ],
          [
            127.499303,
            34.7586765
          ],
          [
            127.4992791,
            34.7586477
          ],
          [
            127.4991971,
            34.7586991
          ],
          [
            127.4991291,
            34.7587431
          ],
          [
            127.4990054,
            34.7588361
          ],
          [
            127.4989355,
            34.7588966
          ],
          [
            127.498803,
            34.7590441
          ],
          [
            127.4987609,
            34.7591042
          ],
          [
            127.4987232,
            34.7591458
          ],
          [
            127.4987057,
            34.7591879
          ],
          [
            127.4987386,
            34.7592671
          ],
          [
            127.4988082,
            34.7593812
          ],
          [
            127.4988412,
            34.7594819
          ],
          [
            127.49888,
            34.7596008
          ],
          [
            127.4988306,
            34.7598998
          ],
          [
            127.498758,
            34.7599963
          ],
          [
            127.4986951,
            34.7600286
          ],
          [
            127.4985942,
            34.7600405
          ],
          [
            127.4984787,
            34.7600778
          ],
          [
            127.4982864,
            34.7601237
          ],
          [
            127.49822,
            34.7601471
          ],
          [
            127.498163,
            34.7601728
          ],
          [
            127.4980871,
            34.7602097
          ],
          [
            127.4980223,
            34.7602665
          ],
          [
            127.4979499,
            34.7603002
          ],
          [
            127.4978805,
            34.7603139
          ],
          [
            127.4977569,
            34.7602497
          ],
          [
            127.4977178,
            34.7601926
          ],
          [
            127.4975412,
            34.7602238
          ],
          [
            127.4974368,
            34.7601955
          ],
          [
            127.4973528,
            34.7602095
          ],
          [
            127.4970336,
            34.7602817
          ],
          [
            127.4966996,
            34.7604131
          ],
          [
            127.4964743,
            34.7605163
          ],
          [
            127.496272,
            34.7606228
          ],
          [
            127.4961498,
            34.7607064
          ],
          [
            127.4958869,
            34.7608582
          ],
          [
            127.495683,
            34.7610611
          ],
          [
            127.4955862,
            34.7611399
          ],
          [
            127.4955668,
            34.7611489
          ],
          [
            127.4955301,
            34.7611673
          ],
          [
            127.4955084,
            34.7612363
          ],
          [
            127.4954905,
            34.7614046
          ],
          [
            127.4955396,
            34.7614553
          ],
          [
            127.4955223,
            34.7615696
          ],
          [
            127.4955152,
            34.7616248
          ],
          [
            127.4954692,
            34.7617604
          ],
          [
            127.495397,
            34.7617964
          ],
          [
            127.4953535,
            34.7619946
          ],
          [
            127.495366,
            34.7620749
          ],
          [
            127.495396,
            34.7621037
          ],
          [
            127.4953912,
            34.7621456
          ],
          [
            127.4953859,
            34.7621709
          ],
          [
            127.4954086,
            34.7622695
          ],
          [
            127.495467,
            34.7623514
          ],
          [
            127.4955166,
            34.7624417
          ],
          [
            127.495546,
            34.7625083
          ],
          [
            127.495638,
            34.7625324
          ],
          [
            127.4956625,
            34.7625758
          ],
          [
            127.4957538,
            34.7626801
          ],
          [
            127.4957836,
            34.7627805
          ],
          [
            127.495831,
            34.7629593
          ],
          [
            127.4958674,
            34.7630213
          ],
          [
            127.4958492,
            34.7630957
          ],
          [
            127.49582,
            34.7631534
          ],
          [
            127.4958281,
            34.7632277
          ],
          [
            127.4959185,
            34.763298
          ],
          [
            127.4959421,
            34.7633501
          ],
          [
            127.49599,
            34.7634837
          ],
          [
            127.4960263,
            34.763553
          ],
          [
            127.4960637,
            34.7636042
          ],
          [
            127.4960653,
            34.7636517
          ],
          [
            127.4960291,
            34.7637143
          ],
          [
            127.4960201,
            34.7637472
          ],
          [
            127.4960045,
            34.7637926
          ],
          [
            127.4960634,
            34.7638349
          ],
          [
            127.4960691,
            34.7638924
          ],
          [
            127.4959557,
            34.7641195
          ],
          [
            127.4959203,
            34.7642087
          ],
          [
            127.495893,
            34.7642645
          ],
          [
            127.4958358,
            34.7643124
          ],
          [
            127.4956194,
            34.7645351
          ],
          [
            127.4955462,
            34.7647026
          ],
          [
            127.4955504,
            34.7647457
          ],
          [
            127.4955525,
            34.7647901
          ],
          [
            127.4955452,
            34.7648456
          ],
          [
            127.4955733,
            34.7648795
          ],
          [
            127.4954996,
            34.7650244
          ],
          [
            127.4954589,
            34.7650665
          ],
          [
            127.4954201,
            34.7651287
          ],
          [
            127.4953737,
            34.7651792
          ],
          [
            127.4954176,
            34.7652461
          ],
          [
            127.4954737,
            34.7652942
          ],
          [
            127.4955154,
            34.7653226
          ],
          [
            127.4954824,
            34.7654087
          ],
          [
            127.4953536,
            34.7654457
          ],
          [
            127.4952596,
            34.7655403
          ],
          [
            127.4951471,
            34.7656244
          ],
          [
            127.4950102,
            34.7656784
          ],
          [
            127.494896,
            34.7657256
          ],
          [
            127.4948111,
            34.7658236
          ],
          [
            127.4947611,
            34.7659005
          ],
          [
            127.4943937,
            34.7659938
          ],
          [
            127.4943117,
            34.7660086
          ],
          [
            127.4940395,
            34.7660373
          ],
          [
            127.4939524,
            34.7660313
          ],
          [
            127.4935989,
            34.7660938
          ],
          [
            127.4934285,
            34.7662283
          ],
          [
            127.4933427,
            34.7662384
          ],
          [
            127.4931044,
            34.7663084
          ],
          [
            127.4929668,
            34.7663473
          ],
          [
            127.4928572,
            34.7663068
          ],
          [
            127.492774,
            34.766311
          ],
          [
            127.4927034,
            34.7663223
          ],
          [
            127.4926807,
            34.7663406
          ],
          [
            127.4926168,
            34.7663779
          ],
          [
            127.4925806,
            34.7663944
          ],
          [
            127.4923603,
            34.7666898
          ],
          [
            127.4922933,
            34.7667762
          ],
          [
            127.4922172,
            34.766798
          ],
          [
            127.4921463,
            34.7668127
          ],
          [
            127.4921188,
            34.7667925
          ],
          [
            127.4920934,
            34.7668131
          ],
          [
            127.4920226,
            34.766834
          ],
          [
            127.4920072,
            34.7668525
          ],
          [
            127.491967,
            34.7668826
          ],
          [
            127.4919204,
            34.7668934
          ],
          [
            127.491905,
            34.7668934
          ],
          [
            127.4918945,
            34.7669136
          ]
        ]
      ],
      [
        [
          [
            127.502736,
            34.7673743
          ],
          [
            127.502583,
            34.7676277
          ],
          [
            127.5022828,
            34.7673991
          ],
          [
            127.5025214,
            34.7669991
          ],
          [
            127.502736,
            34.7673743
          ]
        ]
      ]
    ]
  }
}