{
  "type": "Feature",
  "properties": {
    "gid": "4672033023",
    "lbl": "3856.31",
    "val": 3856.31,
    "gidInfo": {
      "fullCode": "4672033023",
      "fullName": "전라남도 곡성군 석곡면 덕흥리",
      "cityCode": "46",
      "subCode": "720",
      "sub2Code": "330",
      "code": "23",
      "isAlive": true,
      "name": "덕흥리",
      "type": "리"
    }
  },
  "geometry": {
    "type": "MultiPolygon",
    "coordinates": [
      [
        [
          [
            127.2721147,
            35.1547779
          ],
          [
            127.2719057,
            35.1548382
          ],
          [
            127.2716869,
            35.1547401
          ],
          [
            127.2716185,
            35.1545432
          ],
          [
            127.2716013,
            35.1544058
          ],
          [
            127.2715551,
            35.1541436
          ],
          [
            127.271443,
            35.15403
          ],
          [
            127.2711508,
            35.1537415
          ],
          [
            127.2708341,
            35.1536456
          ],
          [
            127.270645,
            35.1536439
          ],
          [
            127.2704066,
            35.1538147
          ],
          [
            127.2690082,
            35.1537408
          ],
          [
            127.2688505,
            35.1536538
          ],
          [
            127.2684828,
            35.1534457
          ],
          [
            127.2679974,
            35.1532407
          ],
          [
            127.2675625,
            35.1530141
          ],
          [
            127.2672953,
            35.1525599
          ],
          [
            127.2672427,
            35.1524706
          ],
          [
            127.2672573,
            35.1518354
          ],
          [
            127.267282,
            35.1514426
          ],
          [
            127.2672156,
            35.1510993
          ],
          [
            127.2670942,
            35.1505502
          ],
          [
            127.2670323,
            35.1502318
          ],
          [
            127.2666269,
            35.1505333
          ],
          [
            127.2662817,
            35.1508348
          ],
          [
            127.2658662,
            35.1509484
          ],
          [
            127.2655904,
            35.1511103
          ],
          [
            127.2647079,
            35.1510187
          ],
          [
            127.2639673,
            35.1511172
          ],
          [
            127.263916,
            35.151124
          ],
          [
            127.2635392,
            35.151426
          ],
          [
            127.2632443,
            35.1516235
          ],
          [
            127.262728,
            35.1513295
          ],
          [
            127.2616359,
            35.1510248
          ],
          [
            127.2612922,
            35.1508668
          ],
          [
            127.2604159,
            35.150901
          ],
          [
            127.2598617,
            35.150614
          ],
          [
            127.2597654,
            35.1505062
          ],
          [
            127.2596498,
            35.1503768
          ],
          [
            127.2593027,
            35.1502871
          ],
          [
            127.2590897,
            35.1500992
          ],
          [
            127.2590482,
            35.1500601
          ],
          [
            127.2587976,
            35.1498021
          ],
          [
            127.2586288,
            35.1496522
          ],
          [
            127.2585783,
            35.1496047
          ],
          [
            127.2585674,
            35.1495941
          ],
          [
            127.2585101,
            35.1495413
          ],
          [
            127.2583216,
            35.1493677
          ],
          [
            127.2581862,
            35.1493059
          ],
          [
            127.2580799,
            35.1492575
          ],
          [
            127.2576677,
            35.1490694
          ],
          [
            127.2575564,
            35.1491417
          ],
          [
            127.2574969,
            35.1491425
          ],
          [
            127.2574034,
            35.1491439
          ],
          [
            127.2569822,
            35.1486461
          ],
          [
            127.2569299,
            35.1485839
          ],
          [
            127.2568839,
            35.1485576
          ],
          [
            127.2567202,
            35.1485834
          ],
          [
            127.2566431,
            35.1485762
          ],
          [
            127.2565341,
            35.1485096
          ],
          [
            127.2565721,
            35.1484911
          ],
          [
            127.2566124,
            35.1484742
          ],
          [
            127.2566569,
            35.1485154
          ],
          [
            127.2567281,
            35.1485251
          ],
          [
            127.256787,
            35.1485127
          ],
          [
            127.2569065,
            35.1484874
          ],
          [
            127.2569375,
            35.1484762
          ],
          [
            127.2570335,
            35.1484415
          ],
          [
            127.2570454,
            35.1484173
          ],
          [
            127.2570993,
            35.1483968
          ],
          [
            127.2571095,
            35.1483628
          ],
          [
            127.2571251,
            35.1483109
          ],
          [
            127.2571597,
            35.148236
          ],
          [
            127.2571335,
            35.1481242
          ],
          [
            127.2571039,
            35.1479898
          ],
          [
            127.2573522,
            35.1478517
          ],
          [
            127.2578522,
            35.1476955
          ],
          [
            127.25794,
            35.1476681
          ],
          [
            127.2583216,
            35.1474322
          ],
          [
            127.2584774,
            35.1473123
          ],
          [
            127.2585874,
            35.1472266
          ],
          [
            127.2593782,
            35.1465485
          ],
          [
            127.2597238,
            35.1462558
          ],
          [
            127.2600773,
            35.1459987
          ],
          [
            127.2601789,
            35.1459251
          ],
          [
            127.2604619,
            35.1456854
          ],
          [
            127.2606584,
            35.145521
          ],
          [
            127.2606797,
            35.1454603
          ],
          [
            127.260805,
            35.145103
          ],
          [
            127.2607683,
            35.1446571
          ],
          [
            127.2607141,
            35.1444026
          ],
          [
            127.2604719,
            35.1435495
          ],
          [
            127.2603312,
            35.1431986
          ],
          [
            127.2601797,
            35.1426372
          ],
          [
            127.2600327,
            35.1421302
          ],
          [
            127.2599318,
            35.1416582
          ],
          [
            127.2598018,
            35.140797
          ],
          [
            127.2597395,
            35.140048
          ],
          [
            127.2596638,
            35.1396402
          ],
          [
            127.2595668,
            35.1391023
          ],
          [
            127.2595092,
            35.1387652
          ],
          [
            127.2592701,
            35.1383013
          ],
          [
            127.2589712,
            35.1379358
          ],
          [
            127.2583953,
            35.1374494
          ],
          [
            127.2582496,
            35.1372377
          ],
          [
            127.2580761,
            35.1368475
          ],
          [
            127.2581844,
            35.1365031
          ],
          [
            127.2582463,
            35.1364137
          ],
          [
            127.2584025,
            35.1361806
          ],
          [
            127.2586648,
            35.1359491
          ],
          [
            127.2589692,
            35.1357917
          ],
          [
            127.2591574,
            35.1356874
          ],
          [
            127.2597213,
            35.1356975
          ],
          [
            127.2600816,
            35.1356942
          ],
          [
            127.2604407,
            35.1356888
          ],
          [
            127.2607974,
            35.1356639
          ],
          [
            127.2611111,
            35.1356428
          ],
          [
            127.2614819,
            35.1355943
          ],
          [
            127.261787,
            35.1355551
          ],
          [
            127.2622361,
            35.1355102
          ],
          [
            127.2627569,
            35.1354555
          ],
          [
            127.2631688,
            35.1354117
          ],
          [
            127.263748,
            35.135293
          ],
          [
            127.2640921,
            35.1351483
          ],
          [
            127.2646331,
            35.1349858
          ],
          [
            127.2650581,
            35.1347581
          ],
          [
            127.2651517,
            35.1346299
          ],
          [
            127.2651826,
            35.1345875
          ],
          [
            127.2653194,
            35.1344008
          ],
          [
            127.2653371,
            35.1343766
          ],
          [
            127.2655711,
            35.1340573
          ],
          [
            127.2656246,
            35.1339793
          ],
          [
            127.2657289,
            35.1338061
          ],
          [
            127.2657869,
            35.1337098
          ],
          [
            127.2658417,
            35.133618
          ],
          [
            127.2658976,
            35.1335098
          ],
          [
            127.2659524,
            35.1334016
          ],
          [
            127.2659838,
            35.1333397
          ],
          [
            127.266106,
            35.1331402
          ],
          [
            127.2662228,
            35.1329871
          ],
          [
            127.2663407,
            35.1328368
          ],
          [
            127.2662881,
            35.13263
          ],
          [
            127.266245,
            35.1324272
          ],
          [
            127.266218,
            35.1322997
          ],
          [
            127.2665494,
            35.1321543
          ],
          [
            127.2667744,
            35.1320144
          ],
          [
            127.267092,
            35.1318617
          ],
          [
            127.2673748,
            35.1317016
          ],
          [
            127.2678924,
            35.1314156
          ],
          [
            127.2683249,
            35.1310413
          ],
          [
            127.2684485,
            35.1307076
          ],
          [
            127.2684932,
            35.1305828
          ],
          [
            127.2687551,
            35.1301939
          ],
          [
            127.2688324,
            35.1300629
          ],
          [
            127.2689369,
            35.1298828
          ],
          [
            127.2690272,
            35.1297263
          ],
          [
            127.2696554,
            35.128878
          ],
          [
            127.2699311,
            35.128513
          ],
          [
            127.2701852,
            35.1286951
          ],
          [
            127.270217,
            35.128708
          ],
          [
            127.2702242,
            35.1287676
          ],
          [
            127.2702445,
            35.1288304
          ],
          [
            127.2702642,
            35.1288535
          ],
          [
            127.2702902,
            35.1288877
          ],
          [
            127.2702917,
            35.1288864
          ],
          [
            127.2703127,
            35.1288907
          ],
          [
            127.2703272,
            35.1288541
          ],
          [
            127.2703498,
            35.1287968
          ],
          [
            127.2706786,
            35.1287315
          ],
          [
            127.2707406,
            35.1287439
          ],
          [
            127.270765,
            35.128769
          ],
          [
            127.2708063,
            35.1287943
          ],
          [
            127.2708248,
            35.1288119
          ],
          [
            127.2708422,
            35.1288415
          ],
          [
            127.2709042,
            35.1289394
          ],
          [
            127.2710047,
            35.1290925
          ],
          [
            127.2710671,
            35.1291242
          ],
          [
            127.2711391,
            35.1291586
          ],
          [
            127.2712491,
            35.1292963
          ],
          [
            127.2713115,
            35.1294909
          ],
          [
            127.2713601,
            35.1295912
          ],
          [
            127.2713914,
            35.1296843
          ],
          [
            127.2713772,
            35.130063
          ],
          [
            127.2713346,
            35.1301846
          ],
          [
            127.27135,
            35.1301967
          ],
          [
            127.2713789,
            35.1302247
          ],
          [
            127.271476,
            35.1302734
          ],
          [
            127.2715533,
            35.1302878
          ],
          [
            127.2716035,
            35.1303098
          ],
          [
            127.2716333,
            35.1304261
          ],
          [
            127.2715828,
            35.1305042
          ],
          [
            127.2716119,
            35.1305504
          ],
          [
            127.2716573,
            35.1306616
          ],
          [
            127.2717176,
            35.1307286
          ],
          [
            127.2716777,
            35.1307882
          ],
          [
            127.2717388,
            35.130905
          ],
          [
            127.2718011,
            35.1309794
          ],
          [
            127.2717761,
            35.1310288
          ],
          [
            127.2717512,
            35.1310908
          ],
          [
            127.2716792,
            35.1311063
          ],
          [
            127.2716129,
            35.1311309
          ],
          [
            127.2715402,
            35.131223
          ],
          [
            127.2713903,
            35.1313589
          ],
          [
            127.271501,
            35.1315054
          ],
          [
            127.2716145,
            35.1316702
          ],
          [
            127.2716572,
            35.1319247
          ],
          [
            127.2716731,
            35.1320305
          ],
          [
            127.2718489,
            35.1321678
          ],
          [
            127.2719374,
            35.1322443
          ],
          [
            127.2720159,
            35.1323074
          ],
          [
            127.2722297,
            35.1325353
          ],
          [
            127.2723256,
            35.1327109
          ],
          [
            127.2723613,
            35.1327763
          ],
          [
            127.2724124,
            35.132855
          ],
          [
            127.2724832,
            35.1329355
          ],
          [
            127.2725155,
            35.1329795
          ],
          [
            127.2726342,
            35.133141
          ],
          [
            127.2724043,
            35.133371
          ],
          [
            127.2722789,
            35.133476
          ],
          [
            127.2721142,
            35.1335968
          ],
          [
            127.2719525,
            35.1337214
          ],
          [
            127.2717874,
            35.1338406
          ],
          [
            127.271686,
            35.1339834
          ],
          [
            127.2715018,
            35.1342117
          ],
          [
            127.271346,
            35.1344296
          ],
          [
            127.2712742,
            35.1345108
          ],
          [
            127.2713531,
            35.1346353
          ],
          [
            127.2715033,
            35.1348868
          ],
          [
            127.2715453,
            35.1350884
          ],
          [
            127.2716008,
            35.1353616
          ],
          [
            127.2716458,
            35.1355242
          ],
          [
            127.2720519,
            35.1357023
          ],
          [
            127.271974,
            35.1360123
          ],
          [
            127.2716343,
            35.13649
          ],
          [
            127.2717164,
            35.1366156
          ],
          [
            127.2718337,
            35.1367935
          ],
          [
            127.271983,
            35.1371348
          ],
          [
            127.2720688,
            35.1373082
          ],
          [
            127.2723617,
            35.1375742
          ],
          [
            127.2725019,
            35.1379504
          ],
          [
            127.2725527,
            35.1380737
          ],
          [
            127.2725469,
            35.1382291
          ],
          [
            127.2725389,
            35.1384447
          ],
          [
            127.2725602,
            35.1387716
          ],
          [
            127.2725164,
            35.1388841
          ],
          [
            127.2724949,
            35.1390898
          ],
          [
            127.2724936,
            35.1391025
          ],
          [
            127.272621,
            35.1393521
          ],
          [
            127.2728236,
            35.1396949
          ],
          [
            127.2729887,
            35.1399075
          ],
          [
            127.2730494,
            35.1399856
          ],
          [
            127.2731104,
            35.1401882
          ],
          [
            127.2732625,
            35.1405328
          ],
          [
            127.2735402,
            35.1408655
          ],
          [
            127.273457,
            35.1410115
          ],
          [
            127.2734226,
            35.1411067
          ],
          [
            127.2734018,
            35.141185
          ],
          [
            127.2734027,
            35.1413943
          ],
          [
            127.2729843,
            35.1418451
          ],
          [
            127.2729774,
            35.1418524
          ],
          [
            127.2729526,
            35.1420949
          ],
          [
            127.2730902,
            35.1423047
          ],
          [
            127.273306,
            35.1425014
          ],
          [
            127.2734695,
            35.1427885
          ],
          [
            127.2734942,
            35.1430215
          ],
          [
            127.2735362,
            35.1432206
          ],
          [
            127.273718,
            35.1434664
          ],
          [
            127.27367,
            35.1436419
          ],
          [
            127.2735841,
            35.144018
          ],
          [
            127.2736518,
            35.144282
          ],
          [
            127.2736889,
            35.1444605
          ],
          [
            127.2736143,
            35.1446801
          ],
          [
            127.2736457,
            35.1448516
          ],
          [
            127.2738083,
            35.1452152
          ],
          [
            127.2740588,
            35.1457507
          ],
          [
            127.2743465,
            35.1463512
          ],
          [
            127.2744252,
            35.1465272
          ],
          [
            127.2746963,
            35.1466869
          ],
          [
            127.2747146,
            35.1466999
          ],
          [
            127.2746266,
            35.147006
          ],
          [
            127.2748045,
            35.1472965
          ],
          [
            127.274846,
            35.1473725
          ],
          [
            127.2746982,
            35.147605
          ],
          [
            127.2742742,
            35.1482549
          ],
          [
            127.2742636,
            35.1484425
          ],
          [
            127.2742595,
            35.1484949
          ],
          [
            127.2746935,
            35.1487013
          ],
          [
            127.2747044,
            35.1487063
          ],
          [
            127.2748312,
            35.1494386
          ],
          [
            127.2748643,
            35.149467
          ],
          [
            127.2752257,
            35.1498485
          ],
          [
            127.2755005,
            35.1499741
          ],
          [
            127.2761336,
            35.1499908
          ],
          [
            127.2767079,
            35.1501398
          ],
          [
            127.276736,
            35.1504393
          ],
          [
            127.2769643,
            35.1507164
          ],
          [
            127.2769091,
            35.1509637
          ],
          [
            127.2764685,
            35.1512785
          ],
          [
            127.2762566,
            35.1515353
          ],
          [
            127.276178,
            35.1516304
          ],
          [
            127.2761037,
            35.1517352
          ],
          [
            127.2760778,
            35.1517658
          ],
          [
            127.2759757,
            35.1519794
          ],
          [
            127.2760324,
            35.1520455
          ],
          [
            127.2760657,
            35.1521443
          ],
          [
            127.2760121,
            35.152224
          ],
          [
            127.2759755,
            35.1523662
          ],
          [
            127.276076,
            35.152468
          ],
          [
            127.2762196,
            35.152846
          ],
          [
            127.2762685,
            35.1531325
          ],
          [
            127.2764573,
            35.1533442
          ],
          [
            127.2767511,
            35.1534895
          ],
          [
            127.276916,
            35.1536337
          ],
          [
            127.2771549,
            35.1537748
          ],
          [
            127.2773519,
            35.1538325
          ],
          [
            127.2773694,
            35.1538419
          ],
          [
            127.2778481,
            35.1542807
          ],
          [
            127.2773166,
            35.1543798
          ],
          [
            127.2771448,
            35.1545834
          ],
          [
            127.2763873,
            35.1547747
          ],
          [
            127.2759929,
            35.1546319
          ],
          [
            127.2752974,
            35.1546029
          ],
          [
            127.2750301,
            35.154686
          ],
          [
            127.2747122,
            35.1546459
          ],
          [
            127.2740351,
            35.1547725
          ],
          [
            127.2738799,
            35.1547684
          ],
          [
            127.2735013,
            35.1547546
          ],
          [
            127.27329,
            35.1546292
          ],
          [
            127.272988,
            35.1545258
          ],
          [
            127.2721147,
            35.1547779
          ]
        ]
      ]
    ]
  }
}