{
  "type": "Feature",
  "properties": {
    "gid": "4723038038",
    "lbl": "2645.80",
    "val": 2645.8,
    "gidInfo": {
      "fullCode": "4723038038",
      "fullName": "경상북도 영천시 고경면 초일리",
      "cityCode": "47",
      "subCode": "230",
      "sub2Code": "380",
      "code": "38",
      "isAlive": true,
      "name": "초일리",
      "type": "리"
    }
  },
  "geometry": {
    "type": "MultiPolygon",
    "coordinates": [
      [
        [
          [
            129.0698797,
            35.9910719
          ],
          [
            129.0700838,
            35.9908136
          ],
          [
            129.0707359,
            35.9903121
          ],
          [
            129.0714091,
            35.9886312
          ],
          [
            129.0706905,
            35.9880842
          ],
          [
            129.0703006,
            35.9876648
          ],
          [
            129.0703087,
            35.9876445
          ],
          [
            129.0708746,
            35.9862053
          ],
          [
            129.0706207,
            35.9860117
          ],
          [
            129.0703299,
            35.9856888
          ],
          [
            129.0704357,
            35.9854603
          ],
          [
            129.0706431,
            35.9850127
          ],
          [
            129.0706233,
            35.9849775
          ],
          [
            129.0703871,
            35.9845538
          ],
          [
            129.0706461,
            35.9843063
          ],
          [
            129.0706263,
            35.984074
          ],
          [
            129.0705617,
            35.9837079
          ],
          [
            129.0704763,
            35.9837012
          ],
          [
            129.0704106,
            35.9826924
          ],
          [
            129.070769,
            35.9822385
          ],
          [
            129.0711532,
            35.9819521
          ],
          [
            129.0705216,
            35.9807756
          ],
          [
            129.0709554,
            35.980592
          ],
          [
            129.0711503,
            35.9801812
          ],
          [
            129.0714042,
            35.9796463
          ],
          [
            129.0714292,
            35.9795908
          ],
          [
            129.071441,
            35.9795713
          ],
          [
            129.0714465,
            35.9793891
          ],
          [
            129.0714697,
            35.9793125
          ],
          [
            129.0714854,
            35.9792604
          ],
          [
            129.0721188,
            35.9789896
          ],
          [
            129.0723359,
            35.9788966
          ],
          [
            129.0727363,
            35.9784987
          ],
          [
            129.0734102,
            35.9778953
          ],
          [
            129.0735778,
            35.9778093
          ],
          [
            129.0736211,
            35.9777873
          ],
          [
            129.0733061,
            35.9769643
          ],
          [
            129.0739131,
            35.976687
          ],
          [
            129.0740759,
            35.9764481
          ],
          [
            129.0742565,
            35.976183
          ],
          [
            129.0739192,
            35.9754656
          ],
          [
            129.0738773,
            35.9751282
          ],
          [
            129.0738523,
            35.9748745
          ],
          [
            129.0739028,
            35.974719
          ],
          [
            129.074156,
            35.9738829
          ],
          [
            129.0743511,
            35.9732382
          ],
          [
            129.0741279,
            35.9727584
          ],
          [
            129.0747035,
            35.9719607
          ],
          [
            129.074555,
            35.9716586
          ],
          [
            129.0744071,
            35.9713582
          ],
          [
            129.074185,
            35.9711741
          ],
          [
            129.0742942,
            35.9701033
          ],
          [
            129.0745611,
            35.969806
          ],
          [
            129.0745479,
            35.9693805
          ],
          [
            129.074687,
            35.9688912
          ],
          [
            129.0749937,
            35.9686144
          ],
          [
            129.0750453,
            35.9685679
          ],
          [
            129.0754796,
            35.9685406
          ],
          [
            129.0758295,
            35.9687063
          ],
          [
            129.0758473,
            35.9686846
          ],
          [
            129.0764262,
            35.9679787
          ],
          [
            129.0769959,
            35.9671907
          ],
          [
            129.0774963,
            35.9669566
          ],
          [
            129.0787315,
            35.9665787
          ],
          [
            129.0792469,
            35.9658706
          ],
          [
            129.0792827,
            35.9658213
          ],
          [
            129.0793583,
            35.9655759
          ],
          [
            129.079345,
            35.965461
          ],
          [
            129.0792146,
            35.9651068
          ],
          [
            129.0795247,
            35.9635816
          ],
          [
            129.0795725,
            35.9633472
          ],
          [
            129.0797607,
            35.963469
          ],
          [
            129.0800801,
            35.9636756
          ],
          [
            129.0806312,
            35.9633865
          ],
          [
            129.0807243,
            35.9633377
          ],
          [
            129.0813792,
            35.9630923
          ],
          [
            129.0816408,
            35.9625012
          ],
          [
            129.0824272,
            35.96249
          ],
          [
            129.0824895,
            35.9624891
          ],
          [
            129.0830503,
            35.962522
          ],
          [
            129.0833339,
            35.9618827
          ],
          [
            129.0834488,
            35.9616224
          ],
          [
            129.0839188,
            35.9608991
          ],
          [
            129.0847835,
            35.9611016
          ],
          [
            129.0860301,
            35.9612278
          ],
          [
            129.0862099,
            35.9612459
          ],
          [
            129.0868532,
            35.9613111
          ],
          [
            129.0869926,
            35.9616909
          ],
          [
            129.0870053,
            35.9617258
          ],
          [
            129.0869967,
            35.9619709
          ],
          [
            129.0869908,
            35.9623012
          ],
          [
            129.0877153,
            35.9627144
          ],
          [
            129.0877262,
            35.9630439
          ],
          [
            129.0873546,
            35.9636576
          ],
          [
            129.0873367,
            35.964008
          ],
          [
            129.0877751,
            35.9640719
          ],
          [
            129.0878161,
            35.9641116
          ],
          [
            129.0879891,
            35.9642782
          ],
          [
            129.0883404,
            35.964617
          ],
          [
            129.088539,
            35.9648185
          ],
          [
            129.0886528,
            35.9650274
          ],
          [
            129.0894009,
            35.9654789
          ],
          [
            129.0895126,
            35.9655447
          ],
          [
            129.0897983,
            35.965796
          ],
          [
            129.0906127,
            35.9665119
          ],
          [
            129.0911383,
            35.9669976
          ],
          [
            129.0907052,
            35.9670658
          ],
          [
            129.0899317,
            35.9671767
          ],
          [
            129.08993,
            35.9678276
          ],
          [
            129.0894347,
            35.9687312
          ],
          [
            129.0897098,
            35.9693469
          ],
          [
            129.0895386,
            35.9702973
          ],
          [
            129.0879431,
            35.9701892
          ],
          [
            129.0870822,
            35.9709505
          ],
          [
            129.0868197,
            35.9716201
          ],
          [
            129.0860986,
            35.9722259
          ],
          [
            129.0867098,
            35.972903
          ],
          [
            129.086138,
            35.9740888
          ],
          [
            129.0855756,
            35.974463
          ],
          [
            129.085009,
            35.9743983
          ],
          [
            129.084834,
            35.9743773
          ],
          [
            129.0836584,
            35.9742359
          ],
          [
            129.084061,
            35.9754917
          ],
          [
            129.0836433,
            35.9767278
          ],
          [
            129.083294,
            35.9770066
          ],
          [
            129.0833716,
            35.9772566
          ],
          [
            129.0839303,
            35.9790601
          ],
          [
            129.0837539,
            35.9793903
          ],
          [
            129.0836391,
            35.9795991
          ],
          [
            129.0828631,
            35.9798294
          ],
          [
            129.0828819,
            35.9802451
          ],
          [
            129.0832184,
            35.9806118
          ],
          [
            129.0837,
            35.9808917
          ],
          [
            129.0837351,
            35.9810418
          ],
          [
            129.0838319,
            35.9814772
          ],
          [
            129.0836222,
            35.9822408
          ],
          [
            129.0832533,
            35.9825306
          ],
          [
            129.0828894,
            35.9828139
          ],
          [
            129.0824168,
            35.9831891
          ],
          [
            129.0826242,
            35.9835429
          ],
          [
            129.0828231,
            35.9838757
          ],
          [
            129.0829635,
            35.9841175
          ],
          [
            129.0831773,
            35.984481
          ],
          [
            129.08333,
            35.9846338
          ],
          [
            129.0836497,
            35.9848642
          ],
          [
            129.083761,
            35.9852846
          ],
          [
            129.0837824,
            35.9855049
          ],
          [
            129.0840522,
            35.9858328
          ],
          [
            129.084883,
            35.985908
          ],
          [
            129.0849684,
            35.9859839
          ],
          [
            129.0850636,
            35.9860689
          ],
          [
            129.0852417,
            35.9862279
          ],
          [
            129.0851243,
            35.9865888
          ],
          [
            129.0850792,
            35.9875571
          ],
          [
            129.0844179,
            35.9888167
          ],
          [
            129.0843856,
            35.9888784
          ],
          [
            129.0843665,
            35.9890049
          ],
          [
            129.0843013,
            35.989437
          ],
          [
            129.0840169,
            35.990208
          ],
          [
            129.0839809,
            35.9903055
          ],
          [
            129.0836702,
            35.9907785
          ],
          [
            129.0830285,
            35.9917447
          ],
          [
            129.082311,
            35.9922761
          ],
          [
            129.082158,
            35.9925936
          ],
          [
            129.0820394,
            35.9928395
          ],
          [
            129.0820928,
            35.9930617
          ],
          [
            129.0821393,
            35.9932546
          ],
          [
            129.0823247,
            35.9939664
          ],
          [
            129.0806408,
            35.9943754
          ],
          [
            129.0802181,
            35.9948285
          ],
          [
            129.0803285,
            35.9952007
          ],
          [
            129.0803187,
            35.995212
          ],
          [
            129.0798389,
            35.9957708
          ],
          [
            129.0797909,
            35.9958266
          ],
          [
            129.0797919,
            35.9959139
          ],
          [
            129.079797,
            35.9963944
          ],
          [
            129.0782249,
            35.9961507
          ],
          [
            129.0778684,
            35.9957662
          ],
          [
            129.0778513,
            35.9957665
          ],
          [
            129.0776872,
            35.9957677
          ],
          [
            129.0776227,
            35.9957759
          ],
          [
            129.0775616,
            35.9957968
          ],
          [
            129.0774905,
            35.9958289
          ],
          [
            129.0773005,
            35.9959031
          ],
          [
            129.0772913,
            35.995875
          ],
          [
            129.0772819,
            35.9958375
          ],
          [
            129.0771214,
            35.9958232
          ],
          [
            129.0770523,
            35.9958368
          ],
          [
            129.0770133,
            35.9958444
          ],
          [
            129.0769415,
            35.9958991
          ],
          [
            129.0768255,
            35.996071
          ],
          [
            129.0767755,
            35.9961251
          ],
          [
            129.0766444,
            35.9961511
          ],
          [
            129.0766008,
            35.9962196
          ],
          [
            129.0765488,
            35.9962897
          ],
          [
            129.0764723,
            35.9963481
          ],
          [
            129.0762934,
            35.9964369
          ],
          [
            129.075976,
            35.9965486
          ],
          [
            129.0758459,
            35.9966157
          ],
          [
            129.0757694,
            35.9966924
          ],
          [
            129.0757166,
            35.9967316
          ],
          [
            129.0755657,
            35.9969567
          ],
          [
            129.075453,
            35.9972001
          ],
          [
            129.0753389,
            35.9973612
          ],
          [
            129.0752213,
            35.9974757
          ],
          [
            129.0751327,
            35.9974059
          ],
          [
            129.0739681,
            35.9965239
          ],
          [
            129.0733557,
            35.996711
          ],
          [
            129.0726789,
            35.9967956
          ],
          [
            129.0718687,
            35.9964863
          ],
          [
            129.0712032,
            35.9962321
          ],
          [
            129.0711774,
            35.9961826
          ],
          [
            129.070912,
            35.995676
          ],
          [
            129.071027,
            35.9954194
          ],
          [
            129.0712959,
            35.9948188
          ],
          [
            129.0709937,
            35.9940053
          ],
          [
            129.0709924,
            35.9939414
          ],
          [
            129.0709922,
            35.9939338
          ],
          [
            129.0709909,
            35.9938172
          ],
          [
            129.0711832,
            35.9929942
          ],
          [
            129.0711105,
            35.9928151
          ],
          [
            129.0710577,
            35.9926847
          ],
          [
            129.0700515,
            35.9925887
          ],
          [
            129.0700451,
            35.9925318
          ],
          [
            129.0698797,
            35.9910719
          ]
        ]
      ]
    ]
  }
}